horriblesubs_batch_downloader/__init__.py
horriblesubs_batch_downloader/__main__.py
horriblesubs_batch_downloader/base_scraper.py
horriblesubs_batch_downloader/episodes_scraper.py
horriblesubs_batch_downloader/exception.py
horriblesubs_batch_downloader/setup_logger.py
horriblesubs_batch_downloader/show_selector.py
horriblesubs_batch_downloader/shows_scraper.py
horriblesubs_batch_downloader-0.2.6.dist-info/DESCRIPTION.rst
horriblesubs_batch_downloader-0.2.6.dist-info/METADATA
horriblesubs_batch_downloader-0.2.6.dist-info/RECORD
horriblesubs_batch_downloader-0.2.6.dist-info/WHEEL
horriblesubs_batch_downloader-0.2.6.dist-info/entry_points.txt
horriblesubs_batch_downloader-0.2.6.dist-info/metadata.json
horriblesubs_batch_downloader-0.2.6.dist-info/top_level.txt
