Metadata-Version: 2.0
Name: horriblesubs-batch-downloader
Version: 0.2.6
Summary: Download all individual episodes of an anime from HorribleSubs easily
Home-page: https://github.com/jtara1/horriblesubs_batch_downloader
Author: James T
Author-email: jtara@tuta.io
License: UNKNOWN
Platform: UNKNOWN
Requires-Dist: bs4
Requires-Dist: cfscrape
Requires-Dist: click
Requires-Dist: lxml
Requires-Dist: requests
Requires-Dist: six
